drf_multiple_settings/__init__.py
drf_multiple_settings/viewsets.py
drf_multiple_settings/filter_backends/__init__.py
drf_multiple_settings/filter_backends/django_filters.py
drf_multiple_settings-1.0.1.dist-info/LICENSE
drf_multiple_settings-1.0.1.dist-info/METADATA
drf_multiple_settings-1.0.1.dist-info/WHEEL
drf_multiple_settings-1.0.1.dist-info/top_level.txt
drf_multiple_settings-1.0.1.dist-info/RECORD
