Metadata-Version: 2.1
Name: drf-multiple-settings
Version: 1.0.1
Summary: DRF ViewSets supporting different settings for actions
Home-page: https://github.com/NoNameItem/drf-multiple-settings
Author: Artem Vasin
Author-email: nonameitem@me.com
License: UNKNOWN
Platform: UNKNOWN
Classifier: Programming Language :: Python :: 3
Classifier: License :: OSI Approved :: MIT License
Classifier: Operating System :: OS Independent
Requires-Dist: djangorestframework (>=3.0)
